LICENSE
MANIFEST.in
README.rst
setup.py
django_loupe.egg-info/PKG-INFO
django_loupe.egg-info/SOURCES.txt
django_loupe.egg-info/dependency_links.txt
django_loupe.egg-info/not-zip-safe
django_loupe.egg-info/requires.txt
django_loupe.egg-info/top_level.txt
example/__init__.py
example/manage.py
example/settings.py
example/urls.py
loupe/__init__.py
loupe/admin.py
loupe/forms.py
loupe/models.py
loupe/specs.py
loupe/tests.py
loupe/urls.py
loupe/views.py
loupe/media/.DS_Store
loupe/media/css/imgnotes.css
loupe/media/images/spacer.gif
loupe/media/js/jquery.imgareaselect-0.4.js
loupe/media/js/jquery.imgnotes-0.2.js
loupe/templatetags/__init__.py
loupe/templatetags/loupe_tags.py