Metadata-Version: 1.0
Name: django-loupe
Version: 0.1.0
Summary: A simple collaborative image/screenshot review app for Django applications
Home-page: http://bitbucket.org/gregnewman/django-loupe/
Author: Greg Newman
Author-email: greg@20seven.org
License: UNKNOWN
Platform: UNKNOWN
Classifier: Development Status :: 3 - Alpha
Classifier: Environment :: Web Environment
Classifier: Intended Audience :: Developers
Classifier: License :: OSI Approved :: BSD License
Classifier: Operating System :: OS Independent
Classifier: Programming Language :: Python
Classifier: Framework :: Django
